{
    "name": "Global Information",
    "numberOfRequests": {
        "total": 170,
        "ok": 170,
        "ko": 0
    },
    "minResponseTime": {
        "total": 73,
        "ok": 73,
        "ko": 0
    },
    "maxResponseTime": {
        "total": 313,
        "ok": 313,
        "ko": 0
    },
    "meanResponseTime": {
        "total": 99,
        "ok": 99,
        "ko": 0
    },
    "standardDeviation": {
        "total": 57,
        "ok": 57,
        "ko": 0
    },
    "percentiles1": {
        "total": 82,
        "ok": 82,
        "ko": 0
    },
    "percentiles2": {
        "total": 87,
        "ok": 87,
        "ko": 0
    },
    "percentiles3": {
        "total": 307,
        "ok": 307,
        "ko": 0
    },
    "percentiles4": {
        "total": 309,
        "ok": 309,
        "ko": 0
    },
    "group1": {
    "name": "t < 800 ms",
    "count": 170,
    "percentage": 100
},
    "group2": {
    "name": "800 ms < t < 1200 ms",
    "count": 0,
    "percentage": 0
},
    "group3": {
    "name": "t > 1200 ms",
    "count": 0,
    "percentage": 0
},
    "group4": {
    "name": "failed",
    "count": 0,
    "percentage": 0
},
    "meanNumberOfRequestsPerSecond": {
        "total": 5.666666666666667,
        "ok": 5.666666666666667,
        "ko": 0
    }
}